steelseries_sonar_py/__init__.py
steelseries_sonar_py/exceptions.py
steelseries_sonar_py/sonar.py
steelseries_sonar_py-1.2.0.dist-info/LICENSE
steelseries_sonar_py-1.2.0.dist-info/METADATA
steelseries_sonar_py-1.2.0.dist-info/WHEEL
steelseries_sonar_py-1.2.0.dist-info/top_level.txt
steelseries_sonar_py-1.2.0.dist-info/RECORD
