Metadata-Version: 2.1
Name: steelseries-sonar-py
Version: 1.2.0
Summary: Simple Python wrapper for the SteelSeries Sonar API
Home-page: https://github.com/Mark7888/steelseries-sonar-py
Author: Mark7888
Author-email: l.mark7888@gmail.com
Project-URL: Documentation, https://github.com/Mark7888/steelseries-sonar-py/blob/master/README.md
Project-URL: Bug Reports, https://github.com/Mark7888/steelseries-sonar-py/issues
Project-URL: Source Code, https://github.com/Mark7888/steelseries-sonar-py
Keywords: steelseries,sonar,volume,control,sonar-api
Classifier: Development Status :: 5 - Production/Stable
Classifier: Intended Audience :: Developers
Classifier: Topic :: Software Development :: Build Tools
Classifier: Programming Language :: Python :: 3
Classifier: Programming Language :: Python :: 3.1
Classifier: Programming Language :: Python :: 3.2
Classifier: Programming Language :: Python :: 3.3
Classifier: Programming Language :: Python :: 3.4
Classifier: Programming Language :: Python :: 3.5
Classifier: Programming Language :: Python :: 3.6
Classifier: Programming Language :: Python :: 3.7
Classifier: Programming Language :: Python :: 3.8
Classifier: Programming Language :: Python :: 3.9
Classifier: Programming Language :: Python :: 3.10
Classifier: Programming Language :: Python :: 3.11
Classifier: Programming Language :: Python :: 3.12
Classifier: Programming Language :: Python :: 3 :: Only
Classifier: License :: OSI Approved :: MIT License
Classifier: Operating System :: Microsoft :: Windows
Requires-Python: >=3
License-File: LICENSE
Requires-Dist: requests >=2.31.0
